django_memoized_prefetch/__init__.py
django_memoized_prefetch/_config.py
django_memoized_prefetch/_dotted_getattr.py
django_memoized_prefetch/_prefetch.py
django_memoized_prefetch-0.1.2.dist-info/METADATA
django_memoized_prefetch-0.1.2.dist-info/WHEEL
django_memoized_prefetch-0.1.2.dist-info/licenses/LICENSE
django_memoized_prefetch-0.1.2.dist-info/RECORD
