Metadata-Version: 2.4
Name: django-memoized-prefetch
Version: 0.1.2
Summary: A memoized prefetch for Django.
Project-URL: Repository, https://github.com/xelixdev/django-memoized-prefetch
Author-email: Mikuláš Poul <mikulas.poul@xelix.com>, Cameron Hobbs <cameron.hobbs@xelix.com>
License-Expression: MIT
License-File: LICENSE
Keywords: django
Classifier: Development Status :: 5 - Production/Stable
Classifier: Framework :: Django
Classifier: Programming Language :: Python
Classifier: Programming Language :: Python :: 3
Classifier: Programming Language :: Python :: 3.10
Classifier: Programming Language :: Python :: 3.11
Classifier: Programming Language :: Python :: 3.12
Classifier: Programming Language :: Python :: 3.13
Classifier: Programming Language :: Python :: 3.14
Requires-Python: >=3.9
Requires-Dist: django>=4.2
Requires-Dist: lru-dict<2,>=1.3.0
